tests/__init__.py
tests/test_youtube_client.py
youtube_complete_api/__init__.py
youtube_complete_api/youtube_client.py
youtube_complete_api-0.1.0.dist-info/LICENSE
youtube_complete_api-0.1.0.dist-info/METADATA
youtube_complete_api-0.1.0.dist-info/WHEEL
youtube_complete_api-0.1.0.dist-info/top_level.txt
youtube_complete_api-0.1.0.dist-info/RECORD
