Metadata-Version: 2.1
Name: youtube-complete-api
Version: 0.1.0
Summary: A unified Python package for managing YouTube Data and Transcript APIs.
Home-page: https://github.com/yourgithubusername/youtube-complete-api
Author: Your Name
Author-email: your.email@example.com
Project-URL: Bug Reports, https://github.com/yourgithubusername/youtube-complete-api/issues
Project-URL: Source, https://github.com/yourgithubusername/youtube-complete-api
Keywords: youtube api data transcript video
Classifier: Development Status :: 4 - Beta
Classifier: Intended Audience :: Developers
Classifier: Topic :: Software Development :: Libraries
Classifier: License :: OSI Approved :: MIT License
Classifier: Programming Language :: Python :: 3
Classifier: Programming Language :: Python :: 3.6
Classifier: Programming Language :: Python :: 3.7
Classifier: Programming Language :: Python :: 3.8
Classifier: Programming Language :: Python :: 3.9
Requires-Python: >=3.6
License-File: LICENSE
Requires-Dist: youtube-data-api
Requires-Dist: youtube-transcript-api
